Metadata-Version: 1.1
Name: manual-sitemap
Version: 19.6.0
Summary: manually create sitemap config and generate sitemap using it
Home-page: https://github.com/sjquant/manual-sitemap
Author: SJQuant
Author-email: seonujang92@gmail.com
License: MIT
Keywords: sitemap,xml
Platform: UNKNOWN
Classifier: Programming Language :: Python :: 3
Classifier: License :: OSI Approved :: MIT License
Classifier: Operating System :: OS Independent
